slapstack_controls/__init__.py
slapstack_controls/output_converters.py
slapstack_controls/storage_policies.py
slapstack_controls-0.1.1.dist-info/LICENSE
slapstack_controls-0.1.1.dist-info/METADATA
slapstack_controls-0.1.1.dist-info/WHEEL
slapstack_controls-0.1.1.dist-info/top_level.txt
slapstack_controls-0.1.1.dist-info/RECORD
