Metadata-Version: 2.1
Name: slapstack-controls
Version: 0.1.1
Summary: Storage Strategies for the SLAPStack simulation Framework.
Home-page: UNKNOWN
License: UNKNOWN
Platform: UNKNOWN
Requires-Python: >3.6.8
License-File: LICENSE
Requires-Dist: slapstack
Requires-Dist: numpy
